Workbook

Sheet COTIZADOR
A1: COTIZADOR PERSONAL SHOPPER
F2: TRM NEGOCIO: | G2: 3200 | H2: Actualiza aquí: TRM del día + $100
A3: PRODUCTO | B3: CATEGORÍA | C3: PRECIO USA (USD) | D3: TAX | E3: TOTAL USA (USD) | F3: TRM NEGOCIO | G3: COSTO TOTAL COP | H3: PRECIO CLIENTE | I3: GANANCIA TOTAL | J3: ESTADO
B4: Ropa | C4: 60 | D4: =IF(C4="","",C4*7%) -> 4.2 | E4: =IF(C4="","",C4+D4) -> 64.2 | F4: =$G$2 -> 3200 | G4: =IF(E4="","",E4*F4) -> 205440 | H4: =IF(G4="","",ROUNDUP(MAX(G4*(1+K4),G4+L4),-4)) -> 290000 | I4: =IF(H4="","",H4-G4) -> 84560 | J4: =IF(I4="","",IF(I4<0,"PÉRDIDA",IF(I4<L4,"REVISAR","GANANCIA"))) -> GANANCIA | K4: =IFERROR(VLOOKUP(B4,CONFIGURACIÓN!$A$2:$C$39,2,FALSE),0) -> 0.4 | L4: =IFERROR(VLOOKUP(B4,CONFIGURACIÓN!$A$2:$C$39,3,FALSE),0) -> 80000
G5: =IF(E5="","",E5*F5) | H5: =IF(G5="","",ROUNDUP(MAX(G5*(1+K5),G5+L5),-4)) | I5: =IF(H5="","",H5-G5) | J5: =IF(I5="","",IF(I5<0,"PÉRDIDA",IF(I5<L5,"REVISAR","GANANCIA"))) | K5: =IFERROR(VLOOKUP(B5,CONFIGURACIÓN!$A$2:$C$39,2,FALSE),0) -> 0 | L5: =IFERROR(VLOOKUP(B5,CONFIGURACIÓN!$A$2:$C$39,3,FALSE),0) -> 0
G6: =IF(E6="","",E6*F6) | H6: =IF(G6="","",ROUNDUP(MAX(G6*(1+K6),G6+L6),-4)) | I6: =IF(H6="","",H6-G6) | J6: =IF(I6="","",IF(I6<0,"PÉRDIDA",IF(I6<L6,"REVISAR","GANANCIA"))) | K6: =IFERROR(VLOOKUP(B6,CONFIGURACIÓN!$A$2:$C$39,2,FALSE),0) -> 0 | L6: =IFERROR(VLOOKUP(B6,CONFIGURACIÓN!$A$2:$C$39,3,FALSE),0) -> 0
G7: =IF(E7="","",E7*F7) | H7: =IF(G7="","",ROUNDUP(MAX(G7*(1+K7),G7+L7),-4)) | I7: =IF(H7="","",H7-G7) | J7: =IF(I7="","",IF(I7<0,"PÉRDIDA",IF(I7<L7,"REVISAR","GANANCIA"))) | K7: =IFERROR(VLOOKUP(B7,CONFIGURACIÓN!$A$2:$C$39,2,FALSE),0) -> 0 | L7: =IFERROR(VLOOKUP(B7,CONFIGURACIÓN!$A$2:$C$39,3,FALSE),0) -> 0
G8: =IF(E8="","",E8*F8) | H8: =IF(G8="","",ROUNDUP(MAX(G8*(1+K8),G8+L8),-4)) | I8: =IF(H8="","",H8-G8) | J8: =IF(I8="","",IF(I8<0,"PÉRDIDA",IF(I8<L8,"REVISAR","GANANCIA"))) | K8: =IFERROR(VLOOKUP(B8,CONFIGURACIÓN!$A$2:$C$39,2,FALSE),0) -> 0 | L8: =IFERROR(VLOOKUP(B8,CONFIGURACIÓN!$A$2:$C$39,3,FALSE),0) -> 0
G9: =IF(E9="","",E9*F9) | H9: =IF(G9="","",ROUNDUP(MAX(G9*(1+K9),G9+L9),-4)) | I9: =IF(H9="","",H9-G9) | J9: =IF(I9="","",IF(I9<0,"PÉRDIDA",IF(I9<L9,"REVISAR","GANANCIA"))) | K9: =IFERROR(VLOOKUP(B9,CONFIGURACIÓN!$A$2:$C$39,2,FALSE),0) -> 0 | L9: =IFERROR(VLOOKUP(B9,CONFIGURACIÓN!$A$2:$C$39,3,FALSE),0) -> 0
G10: =IF(E10="","",E10*F10) | H10: =IF(G10="","",ROUNDUP(MAX(G10*(1+K10),G10+L10),-4)) | I10: =IF(H10="","",H10-G10) | J10: =IF(I10="","",IF(I10<0,"PÉRDIDA",IF(I10<L10,"REVISAR","GANANCIA"))) | K10: =IFERROR(VLOOKUP(B10,CONFIGURACIÓN!$A$2:$C$39,2,FALSE),0) -> 0 | L10: =IFERROR(VLOOKUP(B10,CONFIGURACIÓN!$A$2:$C$39,3,FALSE),0) -> 0
G11: =IF(E11="","",E11*F11) | H11: =IF(G11="","",ROUNDUP(MAX(G11*(1+K11),G11+L11),-4)) | I11: =IF(H11="","",H11-G11) | J11: =IF(I11="","",IF(I11<0,"PÉRDIDA",IF(I11<L11,"REVISAR","GANANCIA"))) | K11: =IFERROR(VLOOKUP(B11,CONFIGURACIÓN!$A$2:$C$39,2,FALSE),0) -> 0 | L11: =IFERROR(VLOOKUP(B11,CONFIGURACIÓN!$A$2:$C$39,3,FALSE),0) -> 0
G12: =IF(E12="","",E12*F12) | H12: =IF(G12="","",ROUNDUP(MAX(G12*(1+K12),G12+L12),-4)) | I12: =IF(H12="","",H12-G12) | J12: =IF(I12="","",IF(I12<0,"PÉRDIDA",IF(I12<L12,"REVISAR","GANANCIA"))) | K12: =IFERROR(VLOOKUP(B12,CONFIGURACIÓN!$A$2:$C$39,2,FALSE),0) -> 0 | L12: =IFERROR(VLOOKUP(B12,CONFIGURACIÓN!$A$2:$C$39,3,FALSE),0) -> 0
G13: =IF(E13="","",E13*F13) | H13: =IF(G13="","",ROUNDUP(MAX(G13*(1+K13),G13+L13),-4)) | I13: =IF(H13="","",H13-G13) | J13: =IF(I13="","",IF(I13<0,"PÉRDIDA",IF(I13<L13,"REVISAR","GANANCIA"))) | K13: =IFERROR(VLOOKUP(B13,CONFIGURACIÓN!$A$2:$C$39,2,FALSE),0) -> 0 | L13: =IFERROR(VLOOKUP(B13,CONFIGURACIÓN!$A$2:$C$39,3,FALSE),0) -> 0
G14: =IF(E14="","",E14*F14) | H14: =IF(G14="","",ROUNDUP(MAX(G14*(1+K14),G14+L14),-4)) | I14: =IF(H14="","",H14-G14) | J14: =IF(I14="","",IF(I14<0,"PÉRDIDA",IF(I14<L14,"REVISAR","GANANCIA"))) | K14: =IFERROR(VLOOKUP(B14,CONFIGURACIÓN!$A$2:$C$39,2,FALSE),0) -> 0 | L14: =IFERROR(VLOOKUP(B14,CONFIGURACIÓN!$A$2:$C$39,3,FALSE),0) -> 0
G15: =IF(E15="","",E15*F15) | H15: =IF(G15="","",ROUNDUP(MAX(G15*(1+K15),G15+L15),-4)) | I15: =IF(H15="","",H15-G15) | J15: =IF(I15="","",IF(I15<0,"PÉRDIDA",IF(I15<L15,"REVISAR","GANANCIA"))) | K15: =IFERROR(VLOOKUP(B15,CONFIGURACIÓN!$A$2:$C$39,2,FALSE),0) -> 0 | L15: =IFERROR(VLOOKUP(B15,CONFIGURACIÓN!$A$2:$C$39,3,FALSE),0) -> 0
G16: =IF(E16="","",E16*F16) | H16: =IF(G16="","",ROUNDUP(MAX(G16*(1+K16),G16+L16),-4)) | I16: =IF(H16="","",H16-G16) | J16: =IF(I16="","",IF(I16<0,"PÉRDIDA",IF(I16<L16,"REVISAR","GANANCIA"))) | K16: =IFERROR(VLOOKUP(B16,CONFIGURACIÓN!$A$2:$C$39,2,FALSE),0) -> 0 | L16: =IFERROR(VLOOKUP(B16,CONFIGURACIÓN!$A$2:$C$39,3,FALSE),0) -> 0
... G53: =IF(E53="","",E53*F53) | H53: =IF(G53="","",ROUNDUP(MAX(G53*(1+K53),G53+L53),-4)) | I53: =IF(H53="","",H53-G53) | J53: =IF(I53="","",IF(I53<0,"PÉRDIDA",IF(I53<L53,"REVISAR","GANANCIA"))) | K53: =IFERROR(VLOOKUP(B53,CONFIGURACIÓN!$A$2:$C$39,2,FALSE),0) -> 0 | L53: =IFERROR(VLOOKUP(B53,CONFIGURACIÓN!$A$2:$C$39,3,FALSE),0) -> 0
A56: CÓMO USARLO
A57: 1. Actualiza G2 con la TRM del día + $100.
A58: 2. Escribe el producto, selecciona la categoría y coloca el precio en USD.
A59: 3. El TAX se calcula al 7% automáticamente.
A60: 4. El costo total se convierte a COP automáticamente.
A61: 5. El precio cliente aplica el recargo de la categoría y respeta la utilidad mínima.
A62: 6. El precio se redondea SIEMPRE hacia arriba al múltiplo de $10.000.
A63: 7. Ganancia Total = Precio Cliente - Costo Total.
A64: 8. CONFIGURACIÓN contiene todos los porcentajes y mínimos para que puedas modificarlos.

Sheet CONFIGURACIÓN
A1: CATEGORÍA | B1: RECARGO | C1: UTILIDAD MÍNIMA
A2: Ropa | B2: 0.4 | C2: 80000
A3: Tenis | B3: 0.4 | C3: 150000
A4: Bolsos / Morrales | B4: 0.4 | C4: 150000
A5: Gorras | B5: 0.45 | C5: 80000
A6: Carteras | B6: 0.45 | C6: 100000
A7: Billeteras | B7: 0.45 | C7: 80000
A8: Cinturones | B8: 0.45 | C8: 80000
A9: Gafas | B9: 0.45 | C9: 80000
A10: Accesorios | B10: 0.45 | C10: 80000
A11: Chaquetas | B11: 0.45 | C11: 150000
A12: Shorts | B12: 0.4 | C12: 80000
A13: Ropa deportiva | B13: 0.4 | C13: 100000
... A39: SALE / Outlet | B39: 0.5 | C39: 100000
